mux.v
//Siddharth Kalra(211032) and Chitwan Goel 210295
module mux(input_1, input_2, select, output_value);

parameter  N=32;

input [N-1:0] input_1;
input [N-1:0] input_2;
input select;
output [N-1:0] output_value;

assign output_value=(select)? input_2: input_1;

endmodule

adder.v
//Siddharth Kalra(211032) and Chitwan Goel 210295
module adder(input_1, input_2 , output_value);

parameter  N=32;

input [N-1:0] input_1;
input [N-1:0] input_2;
output [N-1:0] output_value;

assign  output_value= input_1 + input_2;

endmodule

alu.v
//Siddharth Kalra(211032) and Chitwan Goel 210295
module alu(instruction, a, b, c, zero);


    input [31:0] instruction;
    input [31:0] a;
    input [31:0] b;
    output [31:0] c;
    output zero;

    wire [31:0] values[24:0];

        assign values[0]= a+b;
        assign values[1]= a-b;
        assign values[2]= a+b;
        assign values[3]= a-b;
        assign values[4]= a+b;
        assign values[5]= a+b;

        assign values[6]= a & b;
        assign values[7]= a | b;
        assign values[8]= a & b;
        assign values[9]= a | b;
        assign values[10]=a << b;
        assign values[11]=a >> b;

        assign values[12]=1;
        assign values[13]=1;

        assign values[14]=(a!=b);
        assign values[15]= (a == b);
        assign values[16]=(a<=b);
        assign values[17]=(a<b);
        assign values[18]=(a>=b);
        assign values[19]=(a>b);

        assign values[20]=0;
        assign values[21]=0;
        assign values[22]=0;

        assign values[23]=(a<b)?1:0;
        assign values[24]=(a<b)?1:0;

        assign zero=(values[instruction[31:26]]==0)?1:0;

        assign c=values[instruction[31:26]];


endmodule

data_mem.v
//Siddharth Kalra(211032) and Chitwan Goel 210295
module data_memory( read_address, write_address, write_enable , data_in, data_out, pc );

        input [31:0] data_in;
        input write_enable;
        input [31:0]write_address;
        input [31:0]read_address;

        output [31:0] data_out;
        input [15:0] pc;
        reg [31:0] mem [65535:0];
        integer i;
        initial begin

            mem[0]=0;//sstores 0
            mem[1]=25;//stores n
        
        mem[2]=14;
        mem[3]= 23;
        mem[4]= 8;
        mem[5]= 12;
        mem[6]= 2;
        mem[7]= 16;
        mem[8]= 9;
        mem[9]= 1;
        mem[10]= 6;
        mem[11]= 19;
        mem[12]= 22;
        mem[13]= 20;
        mem[14]= 17;
        mem[15]= 13;
        mem[16]= 24;
        mem[17]= 7;
        mem[18]= 5;
        mem[19]= 10;
        mem[20]= 25;
        mem[21]= 4;
        mem[22]= 11;
        mem[23]= 18;
        mem[24]= 3;
        mem[25]= 21;
        mem[26]= 15;


        end

        always @(pc) begin
            
            if(write_enable && write_address<=65535) begin
                mem[write_address]=data_in;
            end
            
        end

        assign data_out=(read_address<=65535)?mem[read_address]:0;
        initial begin
	#1990000 
            $display("n = %d", mem[1]);
	$display("Sorted array is: ");
            for(i=2;i<mem[1]+2;i=i+1) $display("%d", mem[i]);
        end

endmodule

control_unit.v
//Siddharth Kalra(211032) and Chitwan Goel 210295
module control_unit(instruction, regin1, regin2, regout, write_enable, aluout1, aluout2, aluin,branch,offset,  data_mem_write_enable, data_mem_base_address, data_mem_offset, data_mem_read_data, data_mem_write_data);

    input [31:0] instruction;
    input [31:0] regin1;
    input [31:0] regin2;
    input [31:0] data_mem_read_data;
    input [31:0] aluin;

    output [31:0] aluout1;
    output [31:0] aluout2;
    output branch;
    output write_enable;
    output [31:0] offset;
    output data_mem_write_enable;
    output [31:0] data_mem_base_address;
    output [31:0] data_mem_offset;
    output [31:0] data_mem_write_data;
    output [31:0] regout;


    wire [5:0]x = instruction[31:26];

    assign aluout1=regin1;
    assign aluout2=(x==4 || x==5 || x==8 || x==9 || x==10 || x==11 || x==24)?instruction[15:0]:regin2;
    assign offset=(x==20 || x==22)?instruction[25:0]:((x==21)?regin1: {instruction[25:21]+instruction[10:0]});//note this offset is not suitable for all jump operations
    assign regout=(x==12)?data_mem_read_data: aluin;
    assign data_mem_base_address=(x==12)?regin1:regin2;
    assign data_mem_write_data=regin1;
    assign data_mem_offset=x==12?instruction[15:0]: {instruction[25:21]+instruction[10:0]};
    assign branch=( x==14 || x==15 || x==16 || x==17 || x==18 || x==19 || x==20 || x==21 || x==22)?1:0;
    assign write_enable=(x==13 || x==14 || x==15 || x==16 || x==17 || x==18 || x==19)?0:1;
    assign data_mem_write_enable=(x==13)?1:0;



endmodule

register.v
//Siddharth Kalra(211032) and Chitwan Goel 210295
module register( read_address1, read_address2, write_address, write_enable , data_in, data_out1, data_out2 , pc);

        input [31:0] data_in;
        input write_enable;
        input [4:0]write_address;
        input [4:0]read_address1;
        input [4:0]read_address2;
        input [15:0]pc;
        output [31:0] data_out1;
        output [31:0] data_out2;

        reg [31:0] mem [31:0]; 

        integer i;
        initial begin
            mem[0]=1;
            for (i = 1; i<32; i=i+1) begin
                mem[i]=0;
            end
            mem[17]=32'b10;
        end

        always @(pc) begin
                #2            
                if(write_enable) begin
                     mem[write_address]=data_in;
                end
            
        end

        assign data_out1 = mem[read_address1];
        assign data_out2 = mem[read_address2];


    // initial begin
    //       #5    
    //       forever begin
    //         $display("%d", mem[0]);
    //         #20;
    //       end
    // end


endmodule

instruction_splitter.v
module instruction_split(instruction, rs1, rs2, rd);

    input [31:0] instruction;

    output[4:0] rs1;
    output[4:0] rs2;
    output[4:0] rd;

    
   assign rd=instruction[25:21];
   assign rs1=instruction[20:16];
   assign rs2=instruction[15:11];


endmodule

instruction_mem.v
module instruction_memory( address , instruction );

    input [15:0] address;
    output [31:0] instruction;
    reg [31:0] mem [65535:0];
    initial begin
//s0 is n, s1 is the base address of the array , s2 stores i, s3 stores j, s4 stores temp

        mem[0]=32'b001100_10000_00000_00000_00000_000000;//loads data stored in address located at t0 and stores the data in s0
        mem[1]=32'b000001_00001_10000_00000_00000_000000;//subtracts one from s0 and stores in t1
        mem[2]=32'b001110_00000_00001_10010_00000_010100;//if value stored in t1 and s2 are equal, the jumps to location 19, ie, the end
        mem[3]=32'b000001_00010_10000_10010_00000_000000;//subtracts s2 from s0 and stores in t2
        mem[4]=32'b000001_00011_00010_00000_00000_000001;//subtracts one from t2 and stores in t3
        mem[5]=32'b001100_10011_01010_00000_00000_000000;//loads data stored in address located at t10 and stores the data in s3
        mem[6]=32'b001110_00000_10011_00011_00000_010010;//if value stored in s3 and t3 are equal, then jumps to instruction 17
        mem[7]=32'b000100_00100_10011_00000_00000_000000;//moves the value of s3 to t4
        mem[8]=32'b000000_00100_00100_10001_00000_000000;//adds value of t4 and s1 and stores the result in t4
        mem[9]=32'b000100_00101_00100_00000_00000_000001;//adds 1 to t4 and stores the result in t5
        mem[10]=32'b001100_00110_00100_00000_00000_000000;//loads the value stored in address located in t4 and stores the result in t6
        mem[11]=32'b001100_00111_00101_00000_00000_000000;//loads the value stored in address located in t5 and stores the result in t7
        mem[12]=32'b010011_00000_00110_00111_00000_010000;//jumps to instruction 15 if the value stored in t6 is less than or equal to the value stored in t7
        mem[13]=32'b000100_10100_00110_00000_00000_000000;//moves t6 to s4
        mem[14]=32'b001101_00000_00111_00100_00000_000000;//stores data stored in register t7 in memory with address in register t4
        mem[15]=32'b001101_00000_10100_00101_00000_000000;//stores data stored in register s4 in memory with address stored in register t5
        mem[16]=32'b000100_10011_10011_00000_00000_000001;//adds one to register s3
        mem[17]=32'b010100_00000_00000_00000_00000_000110;//jumps to ikstruction 5
        mem[18]=32'b000100_10010_10010_00000_00000_000001;//adds one to s2
        mem[19]=32'b010100_00000_00000_00000_00000_000010;//jumps to instruction 1
        mem[20]=32'b010100_00000_00000_00000_00000_010100;//jumps to instruction 20



    end
    assign instruction=(address<=65535)?mem[address]:0;
    // assign instruction = mem[address];


endmodule

main.v
//Siddharth Kalra(211032) and Chitwan Goel 210295
`include "instruction_mem.v"
`include "data_mem.v"
`include "adder.v"
`include "mux.v"
`include "register.v"
`include "control_unit.v"
`include "alu.v"
`include "instruction_splitter.v"

module main(clk, pc, instruction);

    //wires instruction, rs1, rs2, r_dest, d1, d2, write_enable, write_data, data_mem_to_control_data, control_to_data_mem_data, control_to_adder_base, control_to_adder_offset, data_mem_adder_output, data_mem_write_enable, alu_to_control, control_to_alu1, control_to_alu2, alu_zero, control_branch_flag, control_pc_offset, branch_mux_select, if_branch_result, if_not_branch_result, branch_mux_result

    input clk;

    output reg [15:0] pc=0;

    output wire [31:0]instruction;
    wire [4:0] rs1;
    wire [4:0] rs2;
    wire [4:0] r_dest;
    wire [31:0] d1;
    wire [31:0] d2;
    wire write_enable;
    wire [31:0] write_data;
    wire [31:0] data_mem_to_control_data;
    wire [31:0] control_to_data_mem_data;
    wire [31:0] control_to_adder_base;
    wire [31:0] control_to_adder_offset;
    wire [31:0] data_mem_adder_output;
    wire data_mem_write_enable;
    wire [31:0] alu_to_control;
    wire [31:0] control_to_alu1;
    wire [31:0] control_to_alu2;

    wire alu_zero;
    wire control_branch_flag;
    wire [31:0] control_pc_offset;
    wire branch_mux_select;
    wire [31:0] if_branch_result;
    wire [31:0] if_not_branch_result;
    wire [31:0] branch_mux_result;


    instruction_memory uut1(pc, instruction);

    instruction_split uut2(instruction, rs1, rs2, r_dest);

    register uut3(rs1, rs2, r_dest, write_enable , write_data, d1, d2, pc);

    control_unit uut4(instruction, d1, d2, write_data, write_enable, control_to_alu1, control_to_alu2, alu_to_control,control_branch_flag,control_pc_offset,  data_mem_write_enable, control_to_adder_base, control_to_adder_offset, data_mem_to_control_data, control_to_data_mem_data);

    adder uut5_data_mem(control_to_adder_offset, control_to_adder_base, data_mem_adder_output);

    data_memory uut6(data_mem_adder_output, data_mem_adder_output, data_mem_write_enable , control_to_data_mem_data, data_mem_to_control_data, pc);

    alu uut7(instruction, control_to_alu1, control_to_alu2, alu_to_control, alu_zero);

    and uut8(branch_mux_select,control_branch_flag, alu_zero );

    adder uut9_jump(if_not_branch_result, control_pc_offset , if_branch_result);

    wire [31:0] one;
    assign one=32'b1;
    wire [31:0] pc_32_bit;
    assign pc_32_bit={16'b0,pc};

    adder uut10_not_jump(one, pc_32_bit , if_not_branch_result);

    mux  uut11(if_not_branch_result, control_pc_offset, branch_mux_select, branch_mux_result);
    
    // initial begin
    //     forever #10 $display("%d\n", instruction);
    // end


    always @(posedge clk) begin
        pc=branch_mux_result;
    end

    // initial begin
    //     #4;
    //     forever begin
    //          $display( "pc: %d",pc);
    //         #20;
    //     end
    // end
    // initial begin
    //     #100 $finish;
    // end

endmodule

main_tb.v
`include "main.v"

module tb();

    reg clk;
    wire [31:0] instruction;
    wire [15:0] pc;
    main uut(clk, pc, instruction);
    initial begin
        clk=0;
    end
    initial begin
        forever begin
            #10 clk=~clk;
        end
    end



    initial begin
        $dumpfile("main_tb.vcd");
        $dumpvars(0, tb);
        #2000000 $finish;
    end

endmodule

main_tb.vcd
$date
	Sun Apr 16 22:09:46 2023
$end
$version
	Icarus Verilog
$end
$timescale
	1s
$end
$scope module tb $end
$var wire 32 ! instruction [31:0] $end
$var wire 16 " pc [15:0] $end
$var reg 1 # clk $end
$scope module uut $end
$var wire 32 $ alu_to_control [31:0] $end
$var wire 1 % alu_zero $end
$var wire 32 & branch_mux_result [31:0] $end
$var wire 1 ' branch_mux_select $end
$var wire 1 ( clk $end
$var wire 1 ) control_branch_flag $end
$var wire 32 * control_pc_offset [31:0] $end
$var wire 32 + control_to_adder_base [31:0] $end
$var wire 32 , control_to_adder_offset [31:0] $end
$var wire 32 - control_to_alu1 [31:0] $end
$var wire 32 . control_to_alu2 [31:0] $end
$var wire 32 / control_to_data_mem_data [31:0] $end
$var wire 32 0 d1 [31:0] $end
$var wire 32 1 d2 [31:0] $end
$var wire 32 2 data_mem_adder_output [31:0] $end
$var wire 32 3 data_mem_to_control_data [31:0] $end
$var wire 1 4 data_mem_write_enable $end
$var wire 32 5 if_branch_result [31:0] $end
$var wire 32 6 if_not_branch_result [31:0] $end
$var wire 32 7 instruction [31:0] $end
$var wire 32 8 one [31:0] $end
$var wire 32 9 pc_32_bit [31:0] $end
$var wire 5 : r_dest [4:0] $end
$var wire 5 ; rs1 [4:0] $end
$var wire 5 < rs2 [4:0] $end
$var wire 32 = write_data [31:0] $end
$var wire 1 > write_enable $end
$var reg 16 ? pc [15:0] $end
$scope module uut1 $end
$var wire 16 @ address [15:0] $end
$var wire 32 A instruction [31:0] $end
$upscope $end
$scope module uut2 $end
$var wire 32 B instruction [31:0] $end
$var wire 5 C rd [4:0] $end
$var wire 5 D rs1 [4:0] $end
$var wire 5 E rs2 [4:0] $end
$upscope $end
$scope module uut3 $end
$var wire 32 F data_in [31:0] $end
$var wire 32 G data_out1 [31:0] $end
$var wire 32 H data_out2 [31:0] $end
$var wire 16 I pc [15:0] $end
$var wire 5 J read_address1 [4:0] $end
$var wire 5 K read_address2 [4:0] $end
$var wire 5 L write_address [4:0] $end
$var wire 1 > write_enable $end
$var integer 32 M i [31:0] $end
$upscope $end
$scope module uut4 $end
$var wire 32 N aluin [31:0] $end
$var wire 32 O aluout1 [31:0] $end
$var wire 32 P aluout2 [31:0] $end
$var wire 1 ) branch $end
$var wire 32 Q data_mem_base_address [31:0] $end
$var wire 32 R data_mem_offset [31:0] $end
$var wire 32 S data_mem_read_data [31:0] $end
$var wire 32 T data_mem_write_data [31:0] $end
$var wire 1 4 data_mem_write_enable $end
$var wire 32 U instruction [31:0] $end
$var wire 32 V offset [31:0] $end
$var wire 32 W regin1 [31:0] $end
$var wire 32 X regin2 [31:0] $end
$var wire 32 Y regout [31:0] $end
$var wire 1 > write_enable $end
$var wire 6 Z x [5:0] $end
$upscope $end
$scope module uut5_data_mem $end
$var wire 32 [ input_1 [31:0] $end
$var wire 32 \ input_2 [31:0] $end
$var wire 32 ] output_value [31:0] $end
$upscope $end
$scope module uut6 $end
$var wire 32 ^ data_in [31:0] $end
$var wire 32 _ data_out [31:0] $end
$var wire 16 ` pc [15:0] $end
$var wire 32 a read_address [31:0] $end
$var wire 32 b write_address [31:0] $end
$var wire 1 4 write_enable $end
$var integer 32 c i [31:0] $end
$upscope $end
$scope module uut7 $end
$var wire 32 d a [31:0] $end
$var wire 32 e b [31:0] $end
$var wire 32 f c [31:0] $end
$var wire 32 g instruction [31:0] $end
$var wire 1 % zero $end
$upscope $end
$scope module uut9_jump $end
$var wire 32 h input_1 [31:0] $end
$var wire 32 i input_2 [31:0] $end
$var wire 32 j output_value [31:0] $end
$upscope $end
$scope module uut10_not_jump $end
$var wire 32 k input_1 [31:0] $end
$var wire 32 l input_2 [31:0] $end
$var wire 32 m output_value [31:0] $end
$upscope $end
$scope module uut11 $end
$var wire 32 n input_1 [31:0] $end
$var wire 32 o input_2 [31:0] $end
$var wire 32 p output_value [31:0] $end
$var wire 1 ' select $end
$upscope $end
$upscope $end
$upscope $end
$enddefinitions $end
#0
$dumpvars
b1 p
b10000 o
b1 n
b1 m
b0 l
b1 k
b10001 j
b10000 i
b1 h
b110010000000000000000000000000 g
b1 f
b1 e
b1 d
bx c
b1 b
b1 a
b0 `
b101 _
b1 ^
b1 ]
b1 \
b0 [
b1100 Z
b101 Y
b1 X
b1 W
b10000 V
b110010000000000000000000000000 U
b1 T
b101 S
b0 R
b1 Q
b1 P
b1 O
b1 N
b100000 M
b10000 L
b0 K
b0 J
b0 I
b1 H
b1 G
b101 F
b0 E
b0 D
b10000 C
b110010000000000000000000000000 B
b110010000000000000000000000000 A
b0 @
b0 ?
1>
b101 =
b0 <
b0 ;
b10000 :
b0 9
b1 8
b110010000000000000000000000000 7
b1 6
b10001 5
04
b101 3
b1 2
b1 1
b1 0
b1 /
b1 .
b1 -
b0 ,
b1 +
b10000 *
0)
0(
0'
b1 &
0%
b1 $
0#
b0 "
b110010000000000000000000000000 !
$end
#10
b1110 3
b1110 S
b1110 _
b1 *
b1 V
b1 i
b1 o
b100 =
b100 F
b100 Y
b10 2
b10 ]
b10 a
b10 b
b1 ,
b1 R
b1 [
b1 :
b1 C
b1 L
b101 -
b101 O
b101 d
b101 /
b101 T
b101 ^
b101 0
b101 G
b101 W
b10000 ;
b10000 D
b10000 J
b1 Z
b100 $
b100 N
b100 f
b10 &
b10 p
b100001100000000000000000000 !
b100001100000000000000000000 7
b100001100000000000000000000 A
b100001100000000000000000000 B
b100001100000000000000000000 U
b100001100000000000000000000 g
b1 ?
b11 5
b11 j
b10 6
b10 h
b10 m
b10 n
b1 9
b1 l
b1 "
b1 @
b1 I
b1 `
1#
1(
#20
0#
0(
#30
1)
0>
b10100 *
b10100 V
b10100 i
b10100 o
b11001 3
b11001 S
b11001 _
b0 .
b0 P
b0 e
b0 +
b0 Q
b0 \
b10100 2
b10100 ]
b10100 a
b10100 b
b10100 ,
b10100 R
b10100 [
b1 =
b1 F
b1 Y
b0 :
b0 C
b0 L
b100 -
b100 O
b100 d
b100 /
b100 T
b100 ^
b100 0
b100 G
b100 W
b1 ;
b1 D
b1 J
b0 1
b0 H
b0 X
b10010 <
b10010 E
b10010 K
b1110 Z
b1 $
b1 N
b1 f
b11 &
b11 p
b111000000000011001000000010100 !
b111000000000011001000000010100 7
b111000000000011001000000010100 A
b111000000000011001000000010100 B
b111000000000011001000000010100 U
b111000000000011001000000010100 g
b10 ?
b10111 5
b10111 j
b11 6
b11 h
b11 m
b11 n
b10 9
b10 l
b10 "
b10 @
b10 I
b10 `
1#
1(
#40
0#
0(
#50
0)
1>
b10 *
b10 V
b10 i
b10 o
b1110 3
b1110 S
b1110 _
b10 2
b10 ]
b10 a
b10 b
b10 ,
b10 R
b10 [
b101 =
b101 F
b101 Y
b10 :
b10 C
b10 L
b101 -
b101 O
b101 d
b101 /
b101 T
b101 ^
b101 0
b101 G
b101 W
b10000 ;
b10000 D
b10000 J
b1 Z
b101 $
b101 N
b101 f
b100 &
b100 p
b100010100001001000000000000 !
b100010100001001000000000000 7
b100010100001001000000000000 A
b100010100001001000000000000 B
b100010100001001000000000000 U
b100010100001001000000000000 g
b11 ?
b110 5
b110 j
b100 6
b100 h
b100 m
b100 n
b11 9
b11 l
b11 "
b11 @
b11 I
b11 `
1#
1(
#60
0#
0(
#70
b100 =
b100 F
b100 Y
b100 *
b100 V
b100 i
b100 o
b1100 3
b1100 S
b1100 _
b100 $
b100 N
b100 f
b1 .
b1 P
b1 e
b1 +
b1 Q
b1 \
b101 2
b101 ]
b101 a
b101 b
b100 ,
b100 R
b100 [
b11 :
b11 C
b11 L
b10 ;
b10 D
b10 J
b1 1
b1 H
b1 X
b0 <
b0 E
b0 K
b101 &
b101 p
b100011000100000000000000001 !
b100011000100000000000000001 7
b100011000100000000000000001 A
b100011000100000000000000001 B
b100011000100000000000000001 U
b100011000100000000000000001 g
b100 ?
b1001 5
b1001 j
b101 6
b101 h
b101 m
b101 n
b100 9
b100 l
b100 "
b100 @
b100 I
b100 `
1#
1(
#80
0#
0(
#90
b10011 *
b10011 V
b10011 i
b10011 o
b0 3
b0 S
b0 _
b0 +
b0 Q
b0 \
b0 2
b0 ]
b0 a
b0 b
b0 ,
b0 R
b0 [
b0 =
b0 F
b0 Y
b10011 :
b10011 C
b10011 L
b0 -
b0 O
b0 d
b0 /
b0 T
b0 ^
b0 0
b0 G
b0 W
b1010 ;
b1010 D
b1010 J
b1100 Z
b1 $
b1 N
b1 f
b110 &
b110 p
b110010011010100000000000000000 !
b110010011010100000000000000000 7
b110010011010100000000000000000 A
b110010011010100000000000000000 B
b110010011010100000000000000000 U
b110010011010100000000000000000 g
b101 ?
b11001 5
b11001 j
b110 6
b110 h
b110 m
b110 n
b101 9
b101 l
b101 "
b101 @
b101 I
b101 `
1#
1(
#100
0#
0(
#110
1)
0>
b10010 *
b10010 V
b10010 i
b10010 o
b1011 3
b1011 S
b1011 _
b100 .
b100 P
b100 e
b1 =
b1 F
b1 Y
b100 +
b100 Q
b100 \
b10110 2
b10110 ]
b10110 a
b10110 b
b10010 ,
b10010 R
b10010 [
b0 :
b0 C
b0 L
b10011 ;
b10011 D
b10011 J
b100 1
b100 H
b100 X
b11 <
b11 E
b11 K
b1110 Z
b111 &
b111 p
b111000000100110001100000010010 !
b111000000100110001100000010010 7
b111000000100110001100000010010 A
b111000000100110001100000010010 B
b111000000100110001100000010010 U
b111000000100110001100000010010 g
b110 ?
b11001 5
b11001 j
b111 6
b111 h
b111 m
b111 n
b110 9
b110 l
b110 "
b110 @
b110 I
b110 `
1#
1(
#120
0#
0(
#130
0)
1%
1>
b100 *
b100 V
b100 i
b100 o
b1100 3
b1100 S
b1100 _
b0 .
b0 P
b0 e
b1 +
b1 Q
b1 \
b101 2
b101 ]
b101 a
b101 b
b100 ,
b100 R
b100 [
b0 =
b0 F
b0 Y
b100 :
b100 C
b100 L
b1 1
b1 H
b1 X
b0 <
b0 E
b0 K
b100 Z
b0 $
b0 N
b0 f
b1000 &
b1000 p
b10000100100110000000000000000 !
b10000100100110000000000000000 7
b10000100100110000000000000000 A
b10000100100110000000000000000 B
b10000100100110000000000000000 U
b10000100100110000000000000000 g
b111 ?
b1100 5
b1100 j
b1000 6
b1000 h
b1000 m
b1000 n
b111 9
b111 l
b111 "
b111 @
b111 I
b111 `
1#
1(
#140
0#
0(
#150
b10 3
b10 S
b10 _
0%
b10 =
b10 F
b10 Y
b110 2
b110 ]
b110 a
b110 b
b10 +
b10 Q
b10 \
b10 $
b10 N
b10 f
b10 .
b10 P
b10 e
b100 ;
b100 D
b100 J
b10 1
b10 H
b10 X
b10001 <
b10001 E
b10001 K
b0 Z
b1001 &
b1001 p
b100001001000100000000000 !
b100001001000100000000000 7
b100001001000100000000000 A
b100001001000100000000000 B
b100001001000100000000000 U
b100001001000100000000000 g
b1000 ?
b1101 5
b1101 j
b1001 6
b1001 h
b1001 m
b1001 n
b1000 9
b1000 l
b1000 "
b1000 @
b1000 I
b1000 `
1#
1(
#152
b100 =
b100 F
b100 Y
b100 $
b100 N
b100 f
b10 -
b10 O
b10 d
b10 /
b10 T
b10 ^
b10 0
b10 G
b10 W
#160
0#
0(
#170
b11 =
b11 F
b11 Y
b110 *
b110 V
b110 i
b110 o
b10000 3
b10000 S
b10000 _
b11 $
b11 N
b11 f
b1 .
b1 P
b1 e
b1 +
b1 Q
b1 \
b111 2
b111 ]
b111 a
b111 b
b110 ,
b110 R
b110 [
b101 :
b101 C
b101 L
b1 1
b1 H
b1 X
b0 <
b0 E
b0 K
b100 Z
b1010 &
b1010 p
b10000101001000000000000000001 !
b10000101001000000000000000001 7
b10000101001000000000000000001 A
b10000101001000000000000000001 B
b10000101001000000000000000001 U
b10000101001000000000000000001 g
b1001 ?
b10000 5
b10000 j
b1010 6
b1010 h
b1010 m
b1010 n
b1001 9
b1001 l
b1001 "
b1001 @
b1001 I
b1001 `
1#
1(
#180
0#
0(
#190
b1110 3
b1110 S
b1110 _
b10 +
b10 Q
b10 \
b1 .
b1 P
b1 e
b10 2
b10 ]
b10 a
b10 b
b0 ,
b0 R
b0 [
b1110 =
b1110 F
b1110 Y
b110 :
b110 C
b110 L
b1100 Z
b1 $
b1 N
b1 f
b1011 &
b1011 p
b110000110001000000000000000000 !
b110000110001000000000000000000 7
b110000110001000000000000000000 A
b110000110001000000000000000000 B
b110000110001000000000000000000 U
b110000110001000000000000000000 g
b1010 ?
b10001 5
b10001 j
b1011 6
b1011 h
b1011 m
b1011 n
b1010 9
b1010 l
b1010 "
b1010 @
b1010 I
b1010 `
1#
1(
#200
0#
0(
#210
b10111 =
b10111 F
b10111 Y
b10111 3
b10111 S
b10111 _
b111 *
b111 V
b111 i
b111 o
b11 2
b11 ]
b11 a
b11 b
b11 +
b11 Q
b11 \
b111 :
b111 C
b111 L
b11 -
b11 O
b11 d
b11 /
b11 T
b11 ^
b11 0
b11 G
b11 W
b101 ;
b101 D
b101 J
b1100 &
b1100 p
b110000111001010000000000000000 !
b110000111001010000000000000000 7
b110000111001010000000000000000 A
b110000111001010000000000000000 B
b110000111001010000000000000000 U
b110000111001010000000000000000 g
b1011 ?
b10011 5
b10011 j
b1100 6
b1100 h
b1100 m
b1100 n
b1011 9
b1011 l
b1011 "
b1011 @
b1011 I
b1011 `
1#
1(
#220
0#
0(
#230
1'
1)
1%
0>
b10000 *
b10000 V
b10000 i
b10000 o
bx 3
bx S
bx _
b0 $
b0 N
b0 f
b10111 .
b10111 P
b10111 e
b0 =
b0 F
b0 Y
b10111 +
b10111 Q
b10111 \
b100111 2
b100111 ]
b100111 a
b100111 b
b10000 ,
b10000 R
b10000 [
b0 :
b0 C
b0 L
b1110 -
b1110 O
b1110 d
b1110 /
b1110 T
b1110 ^
b1110 0
b1110 G
b1110 W
b110 ;
b110 D
b110 J
b10111 1
b10111 H
b10111 X
b111 <
b111 E
b111 K
b10011 Z
b10000 &
b10000 p
b1001100000001100011100000010000 !
b1001100000001100011100000010000 7
b1001100000001100011100000010000 A
b1001100000001100011100000010000 B
b1001100000001100011100000010000 U
b1001100000001100011100000010000 g
b1100 ?
b11101 5
b11101 j
b1101 6
b1101 h
b1101 m
b1101 n
b1100 9
b1100 l
b1100 "
b1100 @
b1100 I
b1100 `
1#
1(
#240
0#
0(
#250
0)
b10001 &
b10001 p
b100 3
b100 S
b100 _
1>
b10100 *
b10100 V
b10100 i
b10100 o
0'
b1 .
b1 P
b1 e
b1 +
b1 Q
b1 \
b10101 2
b10101 ]
b10101 a
b10101 b
b10100 ,
b10100 R
b10100 [
0%
b1 =
b1 F
b1 Y
b10011 :
b10011 C
b10011 L
b0 -
b0 O
b0 d
b0 /
b0 T
b0 ^
b0 0
b0 G
b0 W
b10011 ;
b10011 D
b10011 J
b1 1
b1 H
b1 X
b0 <
b0 E
b0 K
b100 Z
b1 $
b1 N
b1 f
b10010011100110000000000000001 !
b10010011100110000000000000001 7
b10010011100110000000000000001 A
b10010011100110000000000000001 B
b10010011100110000000000000001 U
b10010011100110000000000000001 g
b10000 ?
b100101 5
b100101 j
b10001 6
b10001 h
b10001 m
b10001 n
b10000 9
b10000 l
b10000 "
b10000 @
b10000 I
b10000 `
1#
1(
#252
b10 =
b10 F
b10 Y
b10 $
b10 N
b10 f
b1 -
b1 O
b1 d
b1 /
b1 T
b1 ^
b1 0
b1 G
b1 W
#260
0#
0(
#270
1'
1)
b110 *
b110 V
b110 i
b110 o
b10000 3
b10000 S
b10000 _
b1 .
b1 P
b1 e
b111 2
b111 ]
b111 a
b111 b
b110 ,
b110 R
b110 [
1%
b0 =
b0 F
b0 Y
b0 :
b0 C
b0 L
b0 ;
b0 D
b0 J
b10100 Z
b0 $
b0 N
b0 f
b110 &
b110 p
b1010000000000000000000000000110 !
b1010000000000000000000000000110 7
b1010000000000000000000000000110 A
b1010000000000000000000000000110 B
b1010000000000000000000000000110 U
b1010000000000000000000000000110 g
b10001 ?
b11000 5
b11000 j
b10010 6
b10010 h
b10010 m
b10010 n
b10001 9
b10001 l
b10001 "
b10001 @
b10001 I
b10001 `
1#
1(
#272
b10 3
b10 S
b10 _
b0 .
b0 P
b0 e
b110 2
b110 ]
b110 a
b110 b
b0 +
b0 Q
b0 \
b0 -
b0 O
b0 d
b0 /
b0 T
b0 ^
b0 0
b0 G
b0 W
b0 1
b0 H
b0 X
#280
0#
0(
#290
0>
1)
0'
b111 &
b111 p
b1011 3
b1011 S
b1011 _
0%
b1 =
b1 F
b1 Y
b100 .
b100 P
b100 e
b100 +
b100 Q
b100 \
b10010 *
b10010 V
b10010 i
b10010 o
b10110 2
b10110 ]
b10110 a
b10110 b
b10010 ,
b10010 R
b10010 [
b1 $
b1 N
b1 f
b1 -
b1 O
b1 d
b1 /
b1 T
b1 ^
b1 0
b1 G
b1 W
b10011 ;
b10011 D
b10011 J
b100 1
b100 H
b100 X
b11 <
b11 E
b11 K
b1110 Z
b111000000100110001100000010010 !
b111000000100110001100000010010 7
b111000000100110001100000010010 A
b111000000100110001100000010010 B
b111000000100110001100000010010 U
b111000000100110001100000010010 g
b110 ?
b11001 5
b11001 j
b111 6
b111 h
b111 m
b111 n
b110 9
b110 l
b110 "
b110 @
b110 I
b110 `
1#
1(
#300
0#
0(
#310
0)
1>
b100 *
b100 V
b100 i
b100 o
b1000 3
b1000 S
b1000 _
b0 .
b0 P
b0 e
b0 +
b0 Q
b0 \
b100 2
b100 ]
b100 a
b100 b
b100 ,
b100 R
b100 [
b1 =
b1 F
b1 Y
b100 :
b100 C
b100 L
b0 1
b0 H
b0 X
b0 <
b0 E
b0 K
b100 Z
b1 $
b1 N
b1 f
b1000 &
b1000 p
b10000100100110000000000000000 !
b10000100100110000000000000000 7
b10000100100110000000000000000 A
b10000100100110000000000000000 B
b10000100100110000000000000000 U
b10000100100110000000000000000 g
b111 ?
b1100 5
b1100 j
b1000 6
b1000 h
b1000 m
b1000 n
b111 9
b111 l
b111 "
b111 @
b111 I
b111 `
1#
1(
#320
0#
0(
#330
b10 3
b10 S
b10 _
b11 =
b11 F
b11 Y
b110 2
b110 ]
b110 a
b110 b
b10 +
b10 Q
b10 \
b11 $
b11 N
b11 f
b10 .
b10 P
b10 e
b100 ;
b100 D
b100 J
b10 1
b10 H
b10 X
b10001 <
b10001 E
b10001 K
b0 Z
b1001 &
b1001 p
b100001001000100000000000 !
b100001001000100000000000 7
b100001001000100000000000 A
b100001001000100000000000 B
b100001001000100000000000 U
b100001001000100000000000 g
b1000 ?
b1101 5
b1101 j
b1001 6
b1001 h
b1001 m
b1001 n
b1000 9
b1000 l
b1000 "
b1000 @
b1000 I
b1000 `
1#
1(
#332
b101 =
b101 F
b101 Y
b101 $
b101 N
b101 f
b11 -
b11 O
b11 d
b11 /
b11 T
b11 ^
b11 0
b11 G
b11 W
#340
0#
0(
