mux.v
//Siddharth Kalra(211032) and Chitwan Goel 210295
module mux(input_1, input_2, select, output_value);

parameter  N=32;

input [N-1:0] input_1;
input [N-1:0] input_2;
input select;
output [N-1:0] output_value;

assign output_value=(select)? input_2: input_1;

endmodule

adder.v
//Siddharth Kalra(211032) and Chitwan Goel 210295
module adder(input_1, input_2 , output_value);

parameter  N=32;

input [N-1:0] input_1;
input [N-1:0] input_2;
output [N-1:0] output_value;

assign  output_value= input_1 + input_2;

endmodule

CSE-BUBBLE/alu.v
module alu(instruction, a, b, c, zero);


    input [31:0] instruction;
    input [31:0] a;
    input [31:0] b;
    output [31:0] c;
    output zero;

    wire [31:0] values[24:0];

        assign values[0]= a+b;
        assign values[1]= a-b;
        assign values[2]= a+b;
        assign values[3]= a-b;
        assign values[4]= a+b;
        assign values[5]= a+b;

        assign values[6]= a & b;
        assign values[7]= a | b;
        assign values[8]= a & b;
        assign values[9]= a | b;
        assign values[10]=a << b;
        assign values[11]=a >> b;

        assign values[12]=1;
        assign values[13]=1;

        assign values[14]=(a!=b);
        assign values[15]= (a == b);
        assign values[16]=(a<=b);
        assign values[17]=(a<b);
        assign values[18]=(a>=b);
        assign values[19]=(a>b);

        assign values[20]=0;
        assign values[21]=0;
        assign values[22]=0;

        assign values[23]=(a<b)?1:0;
        assign values[24]=(a<b)?1:0;

        assign zero=(values[instruction[31:26]]==0)?1:0;

        assign c=values[instruction[31:26]];


endmodule

CSE-BUBBLE/data_mem.v
module data_memory( read_address, write_address, write_enable , data_in, data_out, pc );

        input [31:0] data_in;
        input write_enable;
        input [31:0]write_address;
        input [31:0]read_address;

        output [31:0] data_out;
        input [15:0] pc;
        reg [31:0] mem [65535:0];
        integer i;
        initial begin
	// First Dataset
            // mem[0]=0;//sstores 0
            // mem[1]=11;//stores n
            // mem[2]=11;//array sytarts from here
            // mem[3]=7;
            // mem[4]=2;
            // mem[5]=9;
            // mem[6]=8;
            // mem[7]=6;
            // mem[8]=4;
            // mem[9]=5;
            // mem[10]=1;
            // mem[11]=10;
            // mem[12]=3;

	// Second Dataset
            mem[0]=0;//sstores 0
            mem[1]=25;//stores n
        
        mem[2]=14;
        mem[3]= 23;
        mem[4]= 8;
        mem[5]= 12;
        mem[6]= 2;
        mem[7]= 16;
        mem[8]= 9;
        mem[9]= 1;
        mem[10]= 6;
        mem[11]= 19;
        mem[12]= 22;
        mem[13]= 20;
        mem[14]= 17;
        mem[15]= 13;
        mem[16]= 24;
        mem[17]= 7;
        mem[18]= 5;
        mem[19]= 10;
        mem[20]= 25;
        mem[21]= 4;
        mem[22]= 11;
        mem[23]= 18;
        mem[24]= 3;
        mem[25]= 21;
        mem[26]= 15;


        end

        always @(pc) begin
            
            if(write_enable && write_address<=65535) begin
                mem[write_address]=data_in;
            end
            
        end

        assign data_out=(read_address<=65535)?mem[read_address]:0;
        initial begin
	#1990000 
            $display("n = %d", mem[1]);
	$display("Sorted array is: ");
            for(i=2;i<mem[1]+2;i=i+1) $display("%d", mem[i]);
        end

endmodule

CSE-BUBBLE/control_unit.v
module control_unit(instruction, regin1, regin2, regout, write_enable, aluout1, aluout2, aluin,branch,offset,  data_mem_write_enable, data_mem_base_address, data_mem_offset, data_mem_read_data, data_mem_write_data);

    input [31:0] instruction;
    input [31:0] regin1;
    input [31:0] regin2;
    input [31:0] data_mem_read_data;
    input [31:0] aluin;

    output [31:0] aluout1;
    output [31:0] aluout2;
    output branch;
    output write_enable;
    output [31:0] offset;
    output data_mem_write_enable;
    output [31:0] data_mem_base_address;
    output [31:0] data_mem_offset;
    output [31:0] data_mem_write_data;
    output [31:0] regout;


    wire [5:0]x = instruction[31:26];

    assign aluout1=regin1;
    assign aluout2=(x==4 || x==5 || x==8 || x==9 || x==10 || x==11 || x==24)?instruction[15:0]:regin2;
    assign offset=(x==20 || x==22)?instruction[20:0]:((x==21)?regin1: instruction[10:0]);//note this offset is not suitable for all jump operations
    assign regout=(x==12)?data_mem_read_data: aluin;
    assign data_mem_base_address=(x==12)?regin1:regin2;
    assign data_mem_write_data=regin1;
    assign data_mem_offset=x==12?instruction[15:0]: instruction[10:0];
    assign branch=( x==14 || x==15 || x==16 || x==17 || x==18 || x==19 || x==20 || x==21 || x==22)?1:0;
    assign write_enable=(x==13 || x==14 || x==15 || x==16 || x==17 || x==18 || x==19)?0:1;
    assign data_mem_write_enable=(x==13)?1:0;



endmodule

CSE-BUBBLE/register.v
module register( read_address1, read_address2, write_address, write_enable , data_in, data_out1, data_out2 , pc);

        input [31:0] data_in;
        input write_enable;
        input [4:0]write_address;
        input [4:0]read_address1;
        input [4:0]read_address2;
        input [15:0]pc;
        output [31:0] data_out1;
        output [31:0] data_out2;

        reg [31:0] mem [31:0]; 

        integer i;
        initial begin
            mem[0]=1;
            for (i = 1; i<32; i=i+1) begin
                mem[i]=0;
            end
            mem[17]=32'b10;
        end

        always @(pc) begin
                #2            
                if(write_enable) begin
                     mem[write_address]=data_in;
                end
            
        end

        assign data_out1 = mem[read_address1];
        assign data_out2 = mem[read_address2];


    // initial begin
    //       #5    
    //       forever begin
    //         $display("%d", mem[0]);
    //         #20;
    //       end
    // end


endmodule

instruction_splitter.v
module instruction_split(instruction, rs1, rs2, rd);

    input [31:0] instruction;

    output[4:0] rs1;
    output[4:0] rs2;
    output[4:0] rd;

    
   assign rd=instruction[25:21];
   assign rs1=instruction[20:16];
   assign rs2=instruction[15:11];


endmodule

CSE-BUBBLE/instruction_mem.v
module instruction_memory( address , instruction );

    input [15:0] address;
    output [31:0] instruction;
    reg [31:0] mem [65535:0];
    initial begin
//s0 is n, s1 is the base address of the array , s2 stores i, s3 stores j, s4 stores temp

        mem[0]=32'b001100_10000_00000_00000_00000_000000;//loads data stored in address located at t0 and stores the data in s0
        mem[1]=32'b000001_00001_10000_00000_00000_000000;//subtracts one from s0 and stores in t1
        mem[2]=32'b001110_11111_00001_10010_00000_010100;//if value stored in t1 and s2 are equal, the jumps to location 19, ie, the end
        mem[3]=32'b000001_00010_10000_10010_00000_000000;//subtracts s2 from s0 and stores in t2
        mem[4]=32'b000001_00011_00010_00000_00000_000001;//subtracts one from t2 and stores in t3
        mem[5]=32'b001100_10011_01010_00000_00000_000000;//loads data stored in address located at t10 and stores the data in s3
        mem[6]=32'b001110_11111_10011_00011_00000_010010;//if value stored in s3 and t3 are equal, then jumps to instruction 17
        mem[7]=32'b000100_00100_10011_00000_00000_000000;//moves the value of s3 to t4
        mem[8]=32'b000000_00100_00100_10001_00000_000000;//adds value of t4 and s1 and stores the result in t4
        mem[9]=32'b000100_00101_00100_00000_00000_000001;//adds 1 to t4 and stores the result in t5
        mem[10]=32'b001100_00110_00100_00000_00000_000000;//loads the value stored in address located in t4 and stores the result in t6
        mem[11]=32'b001100_00111_00101_00000_00000_000000;//loads the value stored in address located in t5 and stores the result in t7
        mem[12]=32'b010011_11111_00110_00111_00000_010000;//jumps to instruction 15 if the value stored in t6 is less than or equal to the value stored in t7
        mem[13]=32'b000100_10100_00110_00000_00000_000000;//moves t6 to s4
        mem[14]=32'b001101_11111_00111_00100_00000_000000;//stores data stored in register t7 in memory with address in register t4
        mem[15]=32'b001101_11111_10100_00101_00000_000000;//stores data stored in register s4 in memory with address stored in register t5
        mem[16]=32'b000100_10011_10011_00000_00000_000001;//adds one to register s3
        mem[17]=32'b010100_11111_00000_00000_00000_000110;//jumps to ikstruction 5
        mem[18]=32'b000100_10010_10010_00000_00000_000001;//adds one to s2
        mem[19]=32'b010100_11111_00000_00000_00000_000010;//jumps to instruction 1
        mem[20]=32'b010100_11111_00000_00000_00000_010100;//jumps to instruction 20



    end
    assign instruction=(address<=65535)?mem[address]:0;
    // assign instruction = mem[address];


endmodule

CSE-BUBBLE/main.v
`include "instruction_mem.v"
`include "data_mem.v"
`include "adder.v"
`include "mux.v"
`include "register.v"
`include "control_unit.v"
`include "alu.v"
`include "instruction_splitter.v"

module main(clk, pc, instruction);

    //wires instruction, rs1, rs2, r_dest, d1, d2, write_enable, write_data, data_mem_to_control_data, control_to_data_mem_data, control_to_adder_base, control_to_adder_offset, data_mem_adder_output, data_mem_write_enable, alu_to_control, control_to_alu1, control_to_alu2, alu_zero, control_branch_flag, control_pc_offset, branch_mux_select, if_branch_result, if_not_branch_result, branch_mux_result

    input clk;

    output reg [15:0] pc=0;

    output wire [31:0]instruction;
    wire [4:0] rs1;
    wire [4:0] rs2;
    wire [4:0] r_dest;
    wire [31:0] d1;
    wire [31:0] d2;
    wire write_enable;
    wire [31:0] write_data;
    wire [31:0] data_mem_to_control_data;
    wire [31:0] control_to_data_mem_data;
    wire [31:0] control_to_adder_base;
    wire [31:0] control_to_adder_offset;
    wire [31:0] data_mem_adder_output;
    wire data_mem_write_enable;
    wire [31:0] alu_to_control;
    wire [31:0] control_to_alu1;
    wire [31:0] control_to_alu2;

    wire alu_zero;
    wire control_branch_flag;
    wire [31:0] control_pc_offset;
    wire branch_mux_select;
    wire [31:0] if_branch_result;
    wire [31:0] if_not_branch_result;
    wire [31:0] branch_mux_result;


    instruction_memory uut1(pc, instruction);

    instruction_split uut2(instruction, rs1, rs2, r_dest);

    register uut3(rs1, rs2, r_dest, write_enable , write_data, d1, d2, pc);

    control_unit uut4(instruction, d1, d2, write_data, write_enable, control_to_alu1, control_to_alu2, alu_to_control,control_branch_flag,control_pc_offset,  data_mem_write_enable, control_to_adder_base, control_to_adder_offset, data_mem_to_control_data, control_to_data_mem_data);

    adder uut5_data_mem(control_to_adder_offset, control_to_adder_base, data_mem_adder_output);

    data_memory uut6(data_mem_adder_output, data_mem_adder_output, data_mem_write_enable , control_to_data_mem_data, data_mem_to_control_data, pc);

    alu uut7(instruction, control_to_alu1, control_to_alu2, alu_to_control, alu_zero);

    and uut8(branch_mux_select,control_branch_flag, alu_zero );

    adder uut9_jump(if_not_branch_result, control_pc_offset , if_branch_result);

    wire [31:0] one;
    assign one=32'b1;
    wire [31:0] pc_32_bit;
    assign pc_32_bit={16'b0,pc};

    adder uut10_not_jump(one, pc_32_bit , if_not_branch_result);

    mux  uut11(if_not_branch_result, control_pc_offset, branch_mux_select, branch_mux_result);
    
    // initial begin
    //     forever #10 $display("%d\n", instruction);
    // end


    always @(posedge clk) begin
        pc=branch_mux_result;
    end

    // initial begin
    //     #4;
    //     forever begin
    //          $display( "pc: %d",pc);
    //         #20;
    //     end
    // end
    // initial begin
    //     #100 $finish;
    // end

endmodule

CSE-BUBBLE/main_tb.v
`include "main.v"

module tb();

    reg clk;
    wire [31:0] instruction;
    wire [15:0] pc;
    main uut(clk, pc, instruction);
    initial begin
        clk=0;
    end
    initial begin
        forever begin
            #30 clk=~clk;
        end
    end



    initial begin
        $dumpfile("main_tb.vcd");
        $dumpvars(0, tb);
        #2000000 $finish;
    end

endmodule

CSE-BUBBLE/main_tb.vcd
$date
	Sun Apr 16 15:56:29 2023
$end
$version
	Icarus Verilog
$end
$timescale
	1s
$end
$scope module tb $end
$var wire 16 ! pc [15:0] $end
$var wire 32 " instruction [31:0] $end
$var reg 1 # clk $end
$scope module uut $end
$var wire 1 $ branch_mux_select $end
$var wire 1 # clk $end
$var wire 32 % one [31:0] $end
$var wire 1 & write_enable $end
$var wire 32 ' write_data [31:0] $end
$var wire 5 ( rs2 [4:0] $end
$var wire 5 ) rs1 [4:0] $end
$var wire 5 * r_dest [4:0] $end
$var wire 32 + pc_32_bit [31:0] $end
$var wire 32 , instruction [31:0] $end
$var wire 32 - if_not_branch_result [31:0] $end
$var wire 32 . if_branch_result [31:0] $end
$var wire 1 / data_mem_write_enable $end
$var wire 32 0 data_mem_to_control_data [31:0] $end
$var wire 32 1 data_mem_adder_output [31:0] $end
$var wire 32 2 d2 [31:0] $end
$var wire 32 3 d1 [31:0] $end
$var wire 32 4 control_to_data_mem_data [31:0] $end
$var wire 32 5 control_to_alu2 [31:0] $end
$var wire 32 6 control_to_alu1 [31:0] $end
$var wire 32 7 control_to_adder_offset [31:0] $end
$var wire 32 8 control_to_adder_base [31:0] $end
$var wire 32 9 control_pc_offset [31:0] $end
$var wire 1 : control_branch_flag $end
$var wire 32 ; branch_mux_result [31:0] $end
$var wire 1 < alu_zero $end
$var wire 32 = alu_to_control [31:0] $end
$var reg 16 > pc [15:0] $end
$scope module uut1 $end
$var wire 16 ? address [15:0] $end
$var wire 32 @ instruction [31:0] $end
$upscope $end
$scope module uut10_not_jump $end
$var wire 32 A input_1 [31:0] $end
$var wire 32 B input_2 [31:0] $end
$var wire 32 C output_value [31:0] $end
$var parameter 32 D N $end
$upscope $end
$scope module uut11 $end
$var wire 32 E input_1 [31:0] $end
$var wire 1 $ select $end
$var wire 32 F output_value [31:0] $end
$var wire 32 G input_2 [31:0] $end
$var parameter 32 H N $end
$upscope $end
$scope module uut2 $end
$var wire 32 I instruction [31:0] $end
$var wire 5 J rs2 [4:0] $end
$var wire 5 K rs1 [4:0] $end
$var wire 5 L rd [4:0] $end
$upscope $end
$scope module uut3 $end
$var wire 32 M data_out1 [31:0] $end
$var wire 32 N data_out2 [31:0] $end
$var wire 16 O pc [15:0] $end
$var wire 5 P read_address1 [4:0] $end
$var wire 5 Q read_address2 [4:0] $end
$var wire 5 R write_address [4:0] $end
$var wire 1 & write_enable $end
$var wire 32 S data_in [31:0] $end
$var integer 32 T i [31:0] $end
$upscope $end
$scope module uut4 $end
$var wire 32 U aluout1 [31:0] $end
$var wire 32 V data_mem_write_data [31:0] $end
$var wire 32 W instruction [31:0] $end
$var wire 32 X regin1 [31:0] $end
$var wire 32 Y regin2 [31:0] $end
$var wire 6 Z x [5:0] $end
$var wire 1 & write_enable $end
$var wire 32 [ regout [31:0] $end
$var wire 32 \ offset [31:0] $end
$var wire 1 / data_mem_write_enable $end
$var wire 32 ] data_mem_read_data [31:0] $end
$var wire 32 ^ data_mem_offset [31:0] $end
$var wire 32 _ data_mem_base_address [31:0] $end
$var wire 1 : branch $end
$var wire 32 ` aluout2 [31:0] $end
$var wire 32 a aluin [31:0] $end
$upscope $end
$scope module uut5_data_mem $end
$var wire 32 b input_1 [31:0] $end
$var wire 32 c input_2 [31:0] $end
$var wire 32 d output_value [31:0] $end
$var parameter 32 e N $end
$upscope $end
$scope module uut6 $end
$var wire 32 f data_in [31:0] $end
$var wire 16 g pc [15:0] $end
$var wire 32 h read_address [31:0] $end
$var wire 32 i write_address [31:0] $end
$var wire 1 / write_enable $end
$var wire 32 j data_out [31:0] $end
$var integer 32 k i [31:0] $end
$upscope $end
$scope module uut7 $end
$var wire 32 l a [31:0] $end
$var wire 32 m b [31:0] $end
$var wire 32 n c [31:0] $end
$var wire 32 o instruction [31:0] $end
$var wire 1 < zero $end
$upscope $end
$scope module uut9_jump $end
$var wire 32 p input_1 [31:0] $end
$var wire 32 q input_2 [31:0] $end
$var wire 32 r output_value [31:0] $end
$var parameter 32 s N $end
$upscope $end
$upscope $end
$upscope $end
$enddefinitions $end
$comment Show the parameter values. $end
$dumpall
b100000 s
b100000 e
b100000 H
b100000 D
$end
#0
$dumpvars
b1 r
b0 q
b1 p
b110010000000000000000000000000 o
b1 n
b1 m
b1 l
bx k
b11001 j
b1 i
b1 h
b0 g
b1 f
b1 d
b1 c
b0 b
b1 a
b1 `
b1 _
b0 ^
b11001 ]
b0 \
b11001 [
b1100 Z
b1 Y
b1 X
b110010000000000000000000000000 W
b1 V
b1 U
b100000 T
b11001 S
b10000 R
b0 Q
b0 P
b0 O
b1 N
b1 M
b10000 L
b0 K
b0 J
b110010000000000000000000000000 I
b0 G
b1 F
b1 E
b1 C
b0 B
b1 A
b110010000000000000000000000000 @
b0 ?
b0 >
b1 =
0<
b1 ;
0:
b0 9
b1 8
b0 7
b1 6
b1 5
b1 4
b1 3
b1 2
b1 1
b11001 0
0/
b1 .
b1 -
b110010000000000000000000000000 ,
b0 +
b10000 *
b0 )
b0 (
b11001 '
1&
b1 %
0$
0#
b110010000000000000000000000000 "
b0 !
$end
#30
b11000 '
b11000 S
b11000 [
b1 *
b1 L
b1 R
b11001 6
b11001 U
b11001 l
b11001 4
b11001 V
b11001 f
b11001 3
b11001 M
b11001 X
b10000 )
b10000 K
b10000 P
b1 Z
b11000 =
b11000 a
b11000 n
b10 ;
b10 F
b100001100000000000000000000 "
b100001100000000000000000000 ,
b100001100000000000000000000 @
b100001100000000000000000000 I
b100001100000000000000000000 W
b100001100000000000000000000 o
b10 .
b10 r
b10 -
b10 C
b10 E
b10 p
b1 +
b1 B
b1 !
b1 >
b1 ?
b1 O
b1 g
1#
#60
0#
#90
1:
0&
b10100 9
b10100 G
b10100 \
b10100 q
b0 5
b0 `
b0 m
b0 8
b0 _
b0 c
b10100 1
b10100 d
b10100 h
b10100 i
b10100 7
b10100 ^
b10100 b
b1 '
b1 S
b1 [
b11111 *
b11111 L
b11111 R
b11000 6
b11000 U
b11000 l
b11000 4
b11000 V
b11000 f
b11000 3
b11000 M
b11000 X
b1 )
b1 K
b1 P
b0 2
b0 N
b0 Y
b10010 (
b10010 J
b10010 Q
b1110 Z
b1 =
b1 a
b1 n
b11 ;
b11 F
b111011111000011001000000010100 "
b111011111000011001000000010100 ,
b111011111000011001000000010100 @
b111011111000011001000000010100 I
b111011111000011001000000010100 W
b111011111000011001000000010100 o
b10111 .
b10111 r
b11 -
b11 C
b11 E
b11 p
b10 +
b10 B
b10 !
b10 >
b10 ?
b10 O
b10 g
1#
#120
0#
#150
0:
1&
b0 9
b0 G
b0 \
b0 q
b0 0
b0 ]
b0 j
b0 1
b0 d
b0 h
b0 i
b0 7
b0 ^
b0 b
b11001 '
b11001 S
b11001 [
b10 *
b10 L
b10 R
b11001 6
b11001 U
b11001 l
b11001 4
b11001 V
b11001 f
b11001 3
b11001 M
b11001 X
b10000 )
b10000 K
b10000 P
b1 Z
b11001 =
b11001 a
b11001 n
b100 ;
b100 F
b100010100001001000000000000 "
b100010100001001000000000000 ,
b100010100001001000000000000 @
b100010100001001000000000000 I
b100010100001001000000000000 W
b100010100001001000000000000 o
b100 .
b100 r
b100 -
b100 C
b100 E
b100 p
b11 +
b11 B
b11 !
b11 >
b11 ?
b11 O
b11 g
1#
#180
0#
#210
b11000 '
b11000 S
b11000 [
b1 9
b1 G
b1 \
b1 q
b1110 0
b1110 ]
b1110 j
b11000 =
b11000 a
b11000 n
b1 5
b1 `
b1 m
b1 8
b1 _
b1 c
b10 1
b10 d
b10 h
b10 i
b1 7
b1 ^
b1 b
b11 *
b11 L
b11 R
b10 )
b10 K
b10 P
b1 2
b1 N
b1 Y
b0 (
b0 J
b0 Q
b101 ;
b101 F
b100011000100000000000000001 "
b100011000100000000000000001 ,
b100011000100000000000000001 @
b100011000100000000000000001 I
b100011000100000000000000001 W
b100011000100000000000000001 o
b110 .
b110 r
b101 -
b101 C
b101 E
b101 p
b100 +
b100 B
b100 !
b100 >
b100 ?
b100 O
b100 g
1#
#240
0#
#270
b0 9
b0 G
b0 \
b0 q
b0 0
b0 ]
b0 j
b0 8
b0 _
b0 c
b0 1
b0 d
b0 h
b0 i
b0 7
b0 ^
b0 b
b0 '
b0 S
b0 [
b10011 *
b10011 L
b10011 R
b0 6
b0 U
b0 l
b0 4
b0 V
b0 f
b0 3
b0 M
b0 X
b1010 )
b1010 K
b1010 P
b1100 Z
b1 =
b1 a
b1 n
b110 ;
b110 F
b110010011010100000000000000000 "
b110010011010100000000000000000 ,
b110010011010100000000000000000 @
b110010011010100000000000000000 I
b110010011010100000000000000000 W
b110010011010100000000000000000 o
b110 .
b110 r
b110 -
b110 C
b110 E
b110 p
b101 +
b101 B
b101 !
b101 >
b101 ?
b101 O
b101 g
1#
#300
0#
#330
1:
0&
b10010 9
b10010 G
b10010 \
b10010 q
bx 0
bx ]
bx j
b11000 5
b11000 `
b11000 m
b1 '
b1 S
b1 [
b11000 8
b11000 _
b11000 c
b101010 1
b101010 d
b101010 h
b101010 i
b10010 7
b10010 ^
b10010 b
b11111 *
b11111 L
b11111 R
b10011 )
b10011 K
b10011 P
b11000 2
b11000 N
b11000 Y
b11 (
b11 J
b11 Q
b1110 Z
b111 ;
b111 F
b111011111100110001100000010010 "
b111011111100110001100000010010 ,
b111011111100110001100000010010 @
b111011111100110001100000010010 I
b111011111100110001100000010010 W
b111011111100110001100000010010 o
b11001 .
b11001 r
b111 -
b111 C
b111 E
b111 p
b110 +
b110 B
b110 !
b110 >
b110 ?
b110 O
b110 g
1#
#360
0#
#390
0:
1<
1&
b0 9
b0 G
b0 \
b0 q
b11001 0
b11001 ]
b11001 j
b0 5
b0 `
b0 m
b1 8
b1 _
b1 c
b1 1
b1 d
b1 h
b1 i
b0 7
b0 ^
b0 b
b0 '
b0 S
b0 [
b100 *
b100 L
b100 R
b1 2
b1 N
b1 Y
b0 (
b0 J
b0 Q
b100 Z
b0 =
b0 a
b0 n
b1000 ;
b1000 F
b10000100100110000000000000000 "
b10000100100110000000000000000 ,
b10000100100110000000000000000 @
b10000100100110000000000000000 I
b10000100100110000000000000000 W
b10000100100110000000000000000 o
b1000 .
b1000 r
b1000 -
b1000 C
b1000 E
b1000 p
b111 +
b111 B
b111 !
b111 >
b111 ?
b111 O
b111 g
1#
#420
0#
#450
0<
b1110 0
b1110 ]
b1110 j
b10 '
b10 S
b10 [
b10 1
b10 d
b10 h
b10 i
b10 8
b10 _
b10 c
b10 =
b10 a
b10 n
b10 5
b10 `
b10 m
b100 )
b100 K
b100 P
b10 2
b10 N
b10 Y
b10001 (
b10001 J
b10001 Q
b0 Z
b1001 ;
b1001 F
b100001001000100000000000 "
b100001001000100000000000 ,
b100001001000100000000000 @
b100001001000100000000000 I
b100001001000100000000000 W
b100001001000100000000000 o
b1001 .
b1001 r
b1001 -
b1001 C
b1001 E
b1001 p
b1000 +
b1000 B
b1000 !
b1000 >
b1000 ?
b1000 O
b1000 g
1#
#452
b100 '
b100 S
b100 [
b100 =
b100 a
b100 n
b10 6
b10 U
b10 l
b10 4
b10 V
b10 f
b10 3
b10 M
b10 X
#480
0#
#510
b11 '
b11 S
b11 [
b1 9
b1 G
b1 \
b1 q
b11 =
b11 a
b11 n
b1 5
b1 `
b1 m
b1 8
b1 _
b1 c
b10 1
b10 d
b10 h
b10 i
b1 7
b1 ^
b1 b
b101 *
b101 L
b101 R
b1 2
b1 N
b1 Y
b0 (
b0 J
b0 Q
b100 Z
b1010 ;
b1010 F
b10000101001000000000000000001 "
b10000101001000000000000000001 ,
b10000101001000000000000000001 @
b10000101001000000000000000001 I
b10000101001000000000000000001 W
b10000101001000000000000000001 o
b1011 .
b1011 r
b1010 -
b1010 C
b1010 E
b1010 p
b1001 +
b1001 B
b1001 !
b1001 >
b1001 ?
b1001 O
b1001 g
1#
#540
0#
#570
b0 9
b0 G
b0 \
b0 q
b10 8
b10 _
b10 c
b1 5
b1 `
b1 m
b10 1
b10 d
b10 h
b10 i
b0 7
b0 ^
b0 b
b1110 '
b1110 S
b1110 [
b110 *
b110 L
b110 R
b1100 Z
b1 =
b1 a
b1 n
b1011 ;
b1011 F
b110000110001000000000000000000 "
b110000110001000000000000000000 ,
b110000110001000000000000000000 @
b110000110001000000000000000000 I
b110000110001000000000000000000 W
b110000110001000000000000000000 o
b1011 .
b1011 r
b1011 -
b1011 C
b1011 E
b1011 p
b1010 +
b1010 B
b1010 !
b1010 >
b1010 ?
b1010 O
b1010 g
1#
#600
0#
#630
b10111 '
b10111 S
b10111 [
b10111 0
b10111 ]
b10111 j
b11 1
b11 d
b11 h
b11 i
b11 8
b11 _
b11 c
b111 *
b111 L
b111 R
b11 6
b11 U
b11 l
b11 4
b11 V
b11 f
b11 3
b11 M
b11 X
b101 )
b101 K
b101 P
b1100 ;
b1100 F
b110000111001010000000000000000 "
b110000111001010000000000000000 ,
b110000111001010000000000000000 @
b110000111001010000000000000000 I
b110000111001010000000000000000 W
b110000111001010000000000000000 o
b1100 .
b1100 r
b1100 -
b1100 C
b1100 E
b1100 p
b1011 +
b1011 B
b1011 !
b1011 >
b1011 ?
b1011 O
b1011 g
1#
#660
0#
#690
1$
1:
1<
0&
b10000 9
b10000 G
b10000 \
b10000 q
bx 0
bx ]
bx j
b0 =
b0 a
b0 n
b10111 5
b10111 `
b10111 m
b0 '
b0 S
b0 [
b10111 8
b10111 _
b10111 c
b100111 1
b100111 d
b100111 h
b100111 i
b10000 7
b10000 ^
b10000 b
b11111 *
b11111 L
b11111 R
b1110 6
b1110 U
b1110 l
b1110 4
b1110 V
b1110 f
b1110 3
b1110 M
b1110 X
b110 )
b110 K
b110 P
b10111 2
b10111 N
b10111 Y
b111 (
b111 J
b111 Q
b10011 Z
b10000 ;
b10000 F
b1001111111001100011100000010000 "
b1001111111001100011100000010000 ,
b1001111111001100011100000010000 @
b1001111111001100011100000010000 I
b1001111111001100011100000010000 W
b1001111111001100011100000010000 o
b11101 .
b11101 r
b1101 -
b1101 C
b1101 E
b1101 p
b1100 +
b1100 B
b1100 !
b1100 >
b1100 ?
b1100 O
b1100 g
1#
#720
0#
#750
0:
1&
b10001 ;
b10001 F
0$
b1 9
b1 G
b1 \
b1 q
b1110 0
b1110 ]
b1110 j
0<
b1 5
b1 `
b1 m
b1 8
b1 _
b1 c
b10 1
b10 d
b10 h
b10 i
b1 7
b1 ^
b1 b
b1 '
b1 S
b1 [
b10011 *
b10011 L
b10011 R
b0 6
b0 U
b0 l
b0 4
b0 V
b0 f
b0 3
b0 M
b0 X
b10011 )
b10011 K
b10011 P
b1 2
b1 N
b1 Y
b0 (
b0 J
b0 Q
b100 Z
b1 =
b1 a
b1 n
b10010011100110000000000000001 "
b10010011100110000000000000001 ,
b10010011100110000000000000001 @
b10010011100110000000000000001 I
b10010011100110000000000000001 W
b10010011100110000000000000001 o
b10010 .
b10010 r
b10001 -
b10001 C
b10001 E
b10001 p
b10000 +
b10000 B
b10000 !
b10000 >
b10000 ?
b10000 O
b10000 g
1#
#752
b10 '
b10 S
b10 [
b10 =
b10 a
b10 n
b1 6
b1 U
b1 l
b1 4
b1 V
b1 f
b1 3
b1 M
b1 X
#780
0#
#810
1$
1:
b110 9
b110 G
b110 \
b110 q
b10000 0
b10000 ]
b10000 j
1<
b1 5
b1 `
b1 m
b111 1
b111 d
b111 h
b111 i
b110 7
b110 ^
b110 b
b0 '
b0 S
b0 [
b11111 *
b11111 L
b11111 R
b0 )
b0 K
b0 P
b10100 Z
b0 =
b0 a
b0 n
b110 ;
b110 F
b1010011111000000000000000000110 "
b1010011111000000000000000000110 ,
b1010011111000000000000000000110 @
b1010011111000000000000000000110 I
b1010011111000000000000000000110 W
b1010011111000000000000000000110 o
b11000 .
b11000 r
b10010 -
b10010 C
b10010 E
b10010 p
b10001 +
b10001 B
b10001 !
b10001 >
b10001 ?
b10001 O
b10001 g
1#
#840
0#
#870
0&
1:
0$
0<
b1 '
b1 S
b1 [
b111 ;
b111 F
bx 0
bx ]
bx j
b1 =
b1 a
b1 n
b11000 5
b11000 `
b11000 m
b11000 8
b11000 _
b11000 c
b10010 9
b10010 G
b10010 \
b10010 q
b101010 1
b101010 d
b101010 h
b101010 i
b10010 7
b10010 ^
b10010 b
b10011 )
b10011 K
b10011 P
b11000 2
b11000 N
b11000 Y
b11 (
b11 J
b11 Q
b1110 Z
b111011111100110001100000010010 "
b111011111100110001100000010010 ,
b111011111100110001100000010010 @
b111011111100110001100000010010 I
b111011111100110001100000010010 W
b111011111100110001100000010010 o
b11001 .
b11001 r
b111 -
b111 C
b111 E
b111 p
b110 +
b110 B
b110 !
b110 >
b110 ?
b110 O
b110 g
1#
#900
0#
#930
0:
1&
b0 9
b0 G
b0 \
b0 q
b11001 0
b11001 ]
b11001 j
b0 5
b0 `
b0 m
b1 8
b1 _
b1 c
b1 1
b1 d
b1 h
b1 i
b0 7
b0 ^
b0 b
b1 '
b1 S
b1 [
b100 *
b100 L
b100 R
b1 2
b1 N
b1 Y
b0 (
b0 J
b0 Q
b100 Z
b1 =
b1 a
b1 n
b1000 ;
b1000 F
b10000100100110000000000000000 "
b10000100100110000000000000000 ,
b10000100100110000000000000000 @
b10000100100110000000000000000 I
b10000100100110000000000000000 W
b10000100100110000000000000000 o
b1000 .
b1000 r
b1000 -
b1000 C
b1000 E
b1000 p
b111 +
b111 B
b111 !
b111 >
b111 ?
b111 O
b111 g
1#
#960
0#
#990
b1110 0
b1110 ]
b1110 j
b11 '
b11 S
b11 [
b10 1
b10 d
b10 h
b10 i
b10 8
b10 _
b10 c
b11 =
b11 a
b11 n
b10 5
b10 `
b10 m
b100 )
b100 K
b100 P
b10 2
b10 N
b10 Y
b10001 (
b10001 J
b10001 Q
b0 Z
b1001 ;
b1001 F
b100001001000100000000000 "
b100001001000100000000000 ,
b100001001000100000000000 @
b100001001000100000000000 I
b100001001000100000000000 W
b100001001000100000000000 o
b1001 .
b1001 r
b1001 -
b1001 C
b1001 E
b1001 p
b1000 +
b1000 B
b1000 !
b1000 >
b1000 ?
b1000 O
b1000 g
1#
#992
b101 '
b101 S
b101 [
b101 =
b101 a
b101 n
b11 6
b11 U
b11 l
b11 4
b11 V
b11 f
b11 3
b11 M
b11 X
#1020
0#
